qbandas/__init__.py
qbandas/__main__.py
qbandas/_constants.py
qbandas/_pack.py
qbandas/profiles.py
qbandas/records.py
qbandas/schemas.py
qbandas/data/address-fields.json
qbandas/data/config.ini
qbandas/data/field_types.json
qbandas-1.2.1.dist-info/METADATA
qbandas-1.2.1.dist-info/WHEEL
qbandas-1.2.1.dist-info/licenses/LICENSE
qbandas-1.2.1.dist-info/RECORD
