Metadata-Version: 2.1
Name: qbandas
Version: 1.2.1
Summary: Integrates the popular data handling library Pandas and the QuickBase API
Project-URL: homepage, https://pypi.org/project/qbandas/
Project-URL: repository, https://github.com/jhopwood-jjk/qBandas
Project-URL: documentation, https://jhopwood-jjk.github.io/qbandas/index.html
Author: Joshua Hopwood
License-File: LICENSE
Classifier: License :: OSI Approved :: MIT License
Classifier: Operating System :: OS Independent
Classifier: Programming Language :: Python :: 3
Requires-Python: >=3.7
Requires-Dist: pandas==1.4.3
Requires-Dist: requests==2.28.1
